papaille/__init__.py
papaille/__main__.py
papaille/sub_dir/__init__.py
papaille/sub_dir/papaille.py
papaille-0.0.1.dist-info/METADATA
papaille-0.0.1.dist-info/WHEEL
papaille-0.0.1.dist-info/entry_points.txt
papaille-0.0.1.dist-info/top_level.txt
papaille-0.0.1.dist-info/RECORD
