Metadata-Version: 2.1
Name: papaille
Version: 0.0.1
Summary: You write in Python, it compiles to Javascript #Made with ❤️ from west indies
Home-page: UNKNOWN
Author: Guy-Yann VECTOL
Author-email: guyyann.vectol@gmail.com
Maintainer: Guy-Yann VECTOL
Maintainer-email: guyyann.vectol@gmail.com
License: BSD
Project-URL: Transcrypt, https://www.transcrypt.org/
Keywords: transcrypt,pyjs,pytojs,py2js,Vectol,papaille
Platform: UNKNOWN
Classifier: Environment :: Console
Classifier: Environment :: Web Environment
Classifier: Intended Audience :: Developers
Classifier: License :: OSI Approved :: BSD License
Classifier: Operating System :: POSIX :: Linux
Classifier: Programming Language :: Python :: 3
Requires-Python: >=3.6
Requires-Dist: Transcrypt==3.9.3
